parselcode/__init__.py
parselcode/code.csv
parselcode/main.py
parselcode-1.0.0.dist-info/LICENSE
parselcode-1.0.0.dist-info/METADATA
parselcode-1.0.0.dist-info/WHEEL
parselcode-1.0.0.dist-info/top_level.txt
parselcode-1.0.0.dist-info/RECORD
