Metadata-Version: 2.1
Name: parselcode
Version: 1.0.0
Summary: Substitution based Cipher to Encrypt/Decrypt by mapping word structure to hindu birth chart houses
Home-page: https://github.com/Puru-Malhotra/parselcode
Author: Puru Malhotra
Author-email: purumalhotra99@gmail.com
License: MIT
Platform: UNKNOWN
Classifier: License :: OSI Approved :: MIT License
Classifier: Programming Language :: Python :: 3
Classifier: Programming Language :: Python :: 3.7
Requires-Dist: pandas
